Metadata-Version: 2.1
Name: AlgoFnO
Version: 0.0.1
Summary: Bhav Copy Analysis
Home-page: 
Author: Ashutosh Aswani
Author-email: ashutoshaswani2015@gmail.com
License: MIT
Keywords: BhavCopyAnalysis
Platform: UNKNOWN
Classifier: Development Status :: 5 - Production/Stable
Classifier: Intended Audience :: Education
Classifier: Operating System :: Microsoft :: Windows :: Windows 10
Classifier: License :: OSI Approved :: MIT License
Classifier: Programming Language :: Python :: 3
License-File: LICENCE.txt
